{
  "image_id": "Connect (71)",
  "extracted_graph": {
    "diagram_id": "Connect (71)",
    "nodes": [
      {
        "node_id": "start",
        "label_text": "Start",
        "shape_type": "rounded_rectangle",
        "semantic_role": "Terminator"
      },
      {
        "node_id": "reg_q",
        "label_text": "If registered?",
        "shape_type": "diamond",
        "semantic_role": "Decision"
      },
      {
        "node_id": "login",
        "label_text": "Login",
        "shape_type": "rectangle",
        "semantic_role": "Process"
      },
      {
        "node_id": "valid_q",
        "label_text": "Is valid?",
        "shape_type": "diamond",
        "semantic_role": "Decision"
      },
      {
        "node_id": "admin_q",
        "label_text": "Is Admin?",
        "shape_type": "diamond",
        "semantic_role": "Decision"
      },
      {
        "node_id": "reg_p",
        "label_text": "Registration",
        "shape_type": "rectangle",
        "semantic_role": "Process"
      },
      {
        "node_id": "add_info",
        "label_text": "Add\\information",
        "shape_type": "rectangle",
        "semantic_role": "Process"
      },
      {
        "node_id": "update_info",
        "label_text": "Update all\\information",
        "shape_type": "rectangle",
        "semantic_role": "Process"
      },
      {
        "node_id": "travel_info",
        "label_text": "Traveling\\information\\update",
        "shape_type": "rectangle",
        "semantic_role": "Process"
      },
      {
        "node_id": "search",
        "label_text": "Search\\vehicle",
        "shape_type": "rectangle",
        "semantic_role": "Process"
      },
      {
        "node_id": "reserved",
        "label_text": "Car reserved",
        "shape_type": "rectangle",
        "semantic_role": "Process"
      },
      {
        "node_id": "get_id",
        "label_text": "Get ID",
        "shape_type": "rectangle",
        "semantic_role": "Process"
      },
      {
        "node_id": "logout",
        "label_text": "Log out",
        "shape_type": "rectangle",
        "semantic_role": "Process"
      },
      {
        "node_id": "stop",
        "label_text": "Stop",
        "shape_type": "rounded_rectangle",
        "semantic_role": "Terminator"
      }
    ],
    "edges": [
      {
        "edge_id": "edge_1",
        "source_node_id": "start",
        "target_node_id": "reg_q",
        "condition_label": null
      },
      {
        "edge_id": "edge_2",
        "source_node_id": "reg_q",
        "target_node_id": "login",
        "condition_label": "Yes"
      },
      {
        "edge_id": "edge_3",
        "source_node_id": "reg_q",
        "target_node_id": "reg_p",
        "condition_label": "No"
      },
      {
        "edge_id": "edge_4",
        "source_node_id": "reg_p",
        "target_node_id": "login",
        "condition_label": null
      },
      {
        "edge_id": "edge_5",
        "source_node_id": "login",
        "target_node_id": "valid_q",
        "condition_label": null
      },
      {
        "edge_id": "edge_6",
        "source_node_id": "valid_q",
        "target_node_id": "login",
        "condition_label": "No"
      },
      {
        "edge_id": "edge_7",
        "source_node_id": "valid_q",
        "target_node_id": "admin_q",
        "condition_label": "Yes"
      },
      {
        "edge_id": "edge_8",
        "source_node_id": "admin_q",
        "target_node_id": "add_info",
        "condition_label": "Yes"
      },
      {
        "edge_id": "edge_9",
        "source_node_id": "admin_q",
        "target_node_id": "search",
        "condition_label": "No"
      },
      {
        "edge_id": "edge_10",
        "source_node_id": "add_info",
        "target_node_id": "update_info",
        "condition_label": null
      },
      {
        "edge_id": "edge_11",
        "source_node_id": "update_info",
        "target_node_id": "travel_info",
        "condition_label": null
      },
      {
        "edge_id": "edge_12",
        "source_node_id": "search",
        "target_node_id": "reserved",
        "condition_label": null
      },
      {
        "edge_id": "edge_13",
        "source_node_id": "reserved",
        "target_node_id": "get_id",
        "condition_label": null
      },
      {
        "edge_id": "edge_14",
        "source_node_id": "travel_info",
        "target_node_id": "logout",
        "condition_label": null
      },
      {
        "edge_id": "edge_15",
        "source_node_id": "get_id",
        "target_node_id": "logout",
        "condition_label": null
      },
      {
        "edge_id": "edge_16",
        "source_node_id": "logout",
        "target_node_id": "stop",
        "condition_label": null
      }
    ]
  }
}