{
  "image_id": "Normal (221)",
  "extracted_graph": {
    "diagram_id": "Normal (221)",
    "nodes": [
      {
        "node_id": "begin",
        "label_text": "Begin",
        "shape_type": "ellipse",
        "semantic_role": "Terminator"
      },
      {
        "node_id": "init",
        "label_text": "Initialize X < 0",
        "shape_type": "rectangle",
        "semantic_role": "Process"
      },
      {
        "node_id": "inc",
        "label_text": "X=X+2",
        "shape_type": "rectangle",
        "semantic_role": "Process"
      },
      {
        "node_id": "print",
        "label_text": "Print X",
        "shape_type": "trapezium",
        "semantic_role": "Data"
      },
      {
        "node_id": "dec",
        "label_text": "X < 20",
        "shape_type": "diamond",
        "semantic_role": "Decision"
      },
      {
        "node_id": "end",
        "label_text": "END",
        "shape_type": "ellipse",
        "semantic_role": "Terminator"
      }
    ],
    "edges": [
      {
        "edge_id": "edge_1",
        "source_node_id": "begin",
        "target_node_id": "init",
        "condition_label": null
      },
      {
        "edge_id": "edge_2",
        "source_node_id": "init",
        "target_node_id": "inc",
        "condition_label": null
      },
      {
        "edge_id": "edge_3",
        "source_node_id": "inc",
        "target_node_id": "print",
        "condition_label": null
      },
      {
        "edge_id": "edge_4",
        "source_node_id": "print",
        "target_node_id": "dec",
        "condition_label": null
      },
      {
        "edge_id": "edge_5",
        "source_node_id": "dec",
        "target_node_id": "end",
        "condition_label": "NO"
      },
      {
        "edge_id": "edge_6",
        "source_node_id": "dec",
        "target_node_id": "inc",
        "condition_label": "YES"
      }
    ]
  }
}